teserak_regorus-0.1.5.dist-info/METADATA
teserak_regorus-0.1.5.dist-info/WHEEL
teserak_regorus/__init__.py
teserak_regorus/teserak_regorus.cpython-311-darwin.so
teserak_regorus-0.1.5.dist-info/RECORD
