Metadata-Version: 2.3
Name: teserak_regorus
Version: 0.1.5
Classifier: Programming Language :: Rust
Classifier: Programming Language :: Python :: Implementation :: CPython
Classifier: Programming Language :: Python :: Implementation :: PyPy
Summary: Regorus copy - for easy install
Keywords: interpreter,opa,policy-as-code,rego
Requires-Python: >=3.8
Project-URL: Source Code, https://github.com/microsoft/regorus/bindings/python
